{"quote":"… our African-American communities are absolutely in the worst shape they've ever been in before. Ever, ever, ever.","quotePlain":"… our African-American communities are absolutely in the worst shape they’ve ever been in before. Ever, ever, ever.","date":"2016-09-20","person":"donald-trump","name":"Donald Trump","where":"rally in Kenansville, NC","checks":[{"quote":"Trump’s emphatic statement lacked any nuance. There is no comparison between the situation today and slavery, or the situation today and the Jim Crow era. Meanwhile, over the past half-century, African-Americans, despite consistently trailing whites, have made significant strides in life expectancy, educational attainment and other measures, and currently have unemployment and poverty rates that are near historical lows.","quotePlain":"Trump’s emphatic statement lacked any nuance. There is no comparison between the situation today and slavery, or the situation today and the Jim Crow era. Meanwhile, over the past half-century, African-Americans, despite consistently trailing whites, have made significant strides in life expectancy, educational attainment and other measures, and currently have unemployment and poverty rates that are near historical lows.","shareTheFacts":"24e837e9-f924-4bfd-8798-7947f6dfa726","checkerId":"politifact","checker":"PolitiFact"}],"claims":[{"title":"US African-American communities are in the worst shape they've ever been in","negative":"US African-American communities are not in the worst shape they've ever been in","negativePlain":"US African-American communities are not in the worst shape they’ve ever been in","truth":"Slavery? Jim Crow?","truthPlain":"Slavery? Jim Crow?","id":"us-african-american-communities-in-worst-shape-ever"}],"sources":[{"type":"c-span"},{"type":"web"}],"id":"/person/donald-trump/2016-09-20/"}